{
	"ImportPath": "github.com/claassen/gotest",
	"GoVersion": "go1.6",
	"GodepVersion": "v60",
	"Deps": [
		{
			"ImportPath": "github.com/fatih/color",
			"Comment": "v0.1-17-g533cd7f",
			"Rev": "533cd7fd8a85905f67a1753afb4deddc85ea174f"
		},
		{
			"ImportPath": "github.com/mattn/go-colorable",
			"Rev": "9cbef7c35391cca05f15f8181dc0b18bc9736dbb"
		},
		{
			"ImportPath": "github.com/mattn/go-isatty",
			"Rev": "56b76bdf51f7708750eac80fa38b952bb9f32639"
		},
		{
			"ImportPath": "golang.org/x/sys/unix",
			"Rev": "a60af9cbbc6ab800af4f2be864a31f423a0ae1f2"
		}
	]
}
